sensirion_i2c_sts3x/__init__.py
sensirion_i2c_sts3x/commands.py
sensirion_i2c_sts3x/device.py
sensirion_i2c_sts3x/response_provider.py
sensirion_i2c_sts3x/result_types.py
sensirion_i2c_sts3x/version.py
sensirion_i2c_sts3x-1.0.0.dist-info/LICENSE
sensirion_i2c_sts3x-1.0.0.dist-info/METADATA
sensirion_i2c_sts3x-1.0.0.dist-info/WHEEL
sensirion_i2c_sts3x-1.0.0.dist-info/top_level.txt
sensirion_i2c_sts3x-1.0.0.dist-info/RECORD
