Metadata-Version: 2.1
Name: sensirion-i2c-sts3x
Version: 1.0.0
Summary: I2C driver for the Sensirion STS3X sensor family
Home-page: UNKNOWN
Author: Sensirion
Author-email: info@sensirion.com
License: BSD
Project-URL: Documentation, https://sensirion.github.io/python-i2c-sts3x
Project-URL: Repository, https://github.com/Sensirion/python-i2c-sts3x
Project-URL: Changelog, https://github.com/Sensirion/python-i2c-sts3x/blob/master/CHANGELOG.rst
Keywords: Sensirion STS3X
Platform: UNKNOWN
Classifier: Intended Audience :: Developers
Classifier: License :: OSI Approved :: BSD License
Classifier: Programming Language :: Python :: 3.6
Classifier: Programming Language :: Python :: 3.8
Classifier: Topic :: Software Development :: Libraries :: Python Modules
Requires-Python: >=3.6, <4
Requires-Dist: sensirion-i2c-driver (<2.0,>=1.0.0)
Requires-Dist: sensirion-driver-adapters (<3.0,>=2.1.8)
Requires-Dist: sensirion-driver-support-types (~=0.2.0)
Requires-Dist: sensirion-shdlc-sensorbridge (~=0.1.1)
Provides-Extra: docs
Requires-Dist: click (==8.0.4) ; extra == 'docs'
Requires-Dist: jinja2 (==3.0.1) ; extra == 'docs'
Requires-Dist: sphinx (~=4.2.0) ; extra == 'docs'
Requires-Dist: sphinx-rtd-theme (~=0.5.2) ; extra == 'docs'
Provides-Extra: test
Requires-Dist: flake8 (~=3.7.8) ; extra == 'test'
Requires-Dist: pytest (~=6.2.5) ; extra == 'test'
Requires-Dist: pytest-cov (~=3.0.0) ; extra == 'test'
